<?xml version="1.0" encoding="UTF-8"?>
<odoo>
    <record id="hr_rule_l10n_mx_payroll_perception_022_e_04" model="hr.salary.rule">
        <field name="account_debit" ref="cuenta601_08"/>
    </record>
    <record id="hr_rule_l10n_mx_payroll_perception_022_g_04" model="hr.salary.rule">
        <field name="account_debit" ref="cuenta601_08"/>
    </record>
    <record id="hr_rule_l10n_mx_payroll_perception_023_g_1_04" model="hr.salary.rule">
        <field name="account_debit" ref="cuenta601_08"/>
    </record>
    <record id="hr_rule_l10n_mx_payroll_perception_023_e_2_04" model="hr.salary.rule">
        <field name="account_debit" ref="cuenta601_08"/>
    </record>
    <record id="hr_rule_l10n_mx_payroll_perception_023_e_3_04" model="hr.salary.rule">
        <field name="account_debit" ref="cuenta601_08"/>
    </record>
    <record id="hr_rule_l10n_mx_payroll_perception_023_g_3_04" model="hr.salary.rule">
        <field name="account_debit" ref="cuenta601_08"/>
    </record>
    <record id="hr_rule_l10n_mx_payroll_perception_023_g_2_04" model="hr.salary.rule">
        <field name="account_debit" ref="cuenta601_08"/>
    </record>
    <record id="hr_rule_l10n_mx_payroll_perception_025_g_04" model="hr.salary.rule">
        <field name="account_debit" ref="cuenta601_08"/>
    </record>
    <record id="hr_rule_l10n_mx_payroll_perception_025_e_04" model="hr.salary.rule">
        <field name="account_debit" ref="cuenta601_08"/>
    </record>
    <record id="hr_rule_l10n_mx_payroll_deduction_finiquito_002_04" model="hr.salary.rule">
        <field name="account_credit" ref="cuenta210_01"/>
    </record>
    <record id="hr_rule_l10n_mx_payroll_other_payment_002_04" model="hr.salary.rule">
        <field name="account_debit" ref="cuenta601_08"/>
    </record>

    <!-- Sueldo Neto -->
    <record id="hr_rule_net_salary_0_04" model="hr.salary.rule">
        <field name="account_credit" ref="cuenta210_02"/>
    </record>
    <record id="hr_rule_l10n_mx_isn_liquidacion" model="hr.salary.rule">
        <field name="account_debit" ref="cuenta601_08"/>
        <field name="account_credit" ref="cuenta210_01"/>
    </record>
</odoo>
